karaoke_helper/__init__.py
karaoke_helper/db.py
karaoke_helper/example.py
karaoke_helper/wabbit.py
karaoke_helper-0.1.0.dist-info/LICENSE
karaoke_helper-0.1.0.dist-info/METADATA
karaoke_helper-0.1.0.dist-info/WHEEL
karaoke_helper-0.1.0.dist-info/RECORD
